uuidwithdate/__init__.py
uuidwithdate/generator.py
uuid_with_datetime-0.1.0.dist-info/LICENSE
uuid_with_datetime-0.1.0.dist-info/METADATA
uuid_with_datetime-0.1.0.dist-info/WHEEL
uuid_with_datetime-0.1.0.dist-info/top_level.txt
uuid_with_datetime-0.1.0.dist-info/RECORD
